{
	"info": {
		"_postman_id": "dc40f134-a9e4-4212-8038-8d58c58cbfe9",
		"name": "Todo Sam",
		"schema": "https://schema.getpostman.com/json/collection/v2.1.0/collection.json"
	},
	"item": [
		{
			"name": "Todo",
			"request": {
				"method": "GET",
				"header": [],
				"url": {
					"raw": "http://localhost:3000/todo",
					"protocol": "http",
					"host": [
						"localhost"
					],
					"port": "3000",
					"path": [
						"todo"
					]
				}
			},
			"response": []
		},
		{
			"name": "Todo id",
			"request": {
				"method": "GET",
				"header": [],
				"url": {
					"raw": "http://localhost:3000/todo/3",
					"protocol": "http",
					"host": [
						"localhost"
					],
					"port": "3000",
					"path": [
						"todo",
						"3"
					]
				}
			},
			"response": []
		},
		{
			"name": "Todo",
			"request": {
				"method": "POST",
				"header": [],
				"body": {
					"mode": "raw",
					"raw": "{\n    \"title\": \"Hello 2\",\n    \"description\": \"This is hello hello 2\",\n    \"done\": true\n}",
					"options": {
						"raw": {
							"language": "json"
						}
					}
				},
				"url": {
					"raw": "http://localhost:3000/todo",
					"protocol": "http",
					"host": [
						"localhost"
					],
					"port": "3000",
					"path": [
						"todo"
					]
				}
			},
			"response": []
		},
		{
			"name": "Todo",
			"request": {
				"method": "DELETE",
				"header": [],
				"url": {
					"raw": "http://localhost:3000/todo/2",
					"protocol": "http",
					"host": [
						"localhost"
					],
					"port": "3000",
					"path": [
						"todo",
						"2"
					]
				}
			},
			"response": []
		},
		{
			"name": "Todo",
			"request": {
				"method": "PUT",
				"header": [],
				"body": {
					"mode": "raw",
					"raw": "{\n    \"description\": \"Hello description 3\"\n\n}",
					"options": {
						"raw": {
							"language": "json"
						}
					}
				},
				"url": {
					"raw": "http://localhost:3000/todo/3",
					"protocol": "http",
					"host": [
						"localhost"
					],
					"port": "3000",
					"path": [
						"todo",
						"3"
					]
				}
			},
			"response": []
		}
	]
}